cradle/sdk/__init__.py
cradle/sdk/auth/__init__.py
cradle/sdk/auth/device.py
cradle/sdk/client.py
cradle/sdk/exceptions.py
cradle/sdk/types/common.py
cradle/sdk/types/data.py
cradle/sdk/types/task.py
cradle/sdk/types/tasks/common.py
cradle/sdk/types/tasks/v1.py
cradle/sdk/types/tasks/v2.py
cradle/sdk/types/workspace.py
cradle/sdk/uploader.py
cradle/sdk/utils.py
cradle_sdk-0.3.1.dist-info/licenses/LICENSE
cradle_sdk-0.3.1.dist-info/WHEEL
cradle_sdk-0.3.1.dist-info/METADATA
cradle_sdk-0.3.1.dist-info/RECORD
