Metadata-Version: 2.4
Name: cradle-sdk
Version: 0.3.1
Summary: Cradle SDK: A Python SDK for interacting with the Cradle API. For more information, visit https://docs.cradle.bio.
Author: Cradle
Author-email: Cradle <eng@cradle.bio>
License-Expression: MIT
License-File: LICENSE
Requires-Dist: httpx>=0.25.0
Requires-Dist: pyjwt>=2.0.0
Requires-Dist: numpy>=1.23.0,<2.0.0
Requires-Dist: openpyxl>=3.1.0
Requires-Dist: pandas[excel]>=2.2.3
Requires-Dist: pyarrow>=19.0.1
Requires-Dist: pydantic[email]>=2.11.0,<3.0.0
Requires-Dist: keyring>=25.7.0
Requires-Python: >=3.10
